rtl/core/writeback.sv
module writeback (
    input  logic [63:0] alu_result,
    input  logic [63:0] mem_data,
    input  logic        mem_to_reg,

    output logic [63:0] rd_data
);

    assign rd_data = mem_to_reg ? mem_data : alu_result;

endmodule

rtl/core/mem_stage.sv
module mem_stage (
    input  logic [63:0] alu_result,
    input  logic [63:0] rs2_data,
    input  logic        mem_we,

    output logic [63:0] data_mem_addr,
    output logic [63:0] data_mem_wdata,
    output logic        data_mem_we
);

    assign data_mem_addr  = alu_result;
    assign data_mem_wdata = rs2_data;
    assign data_mem_we    = mem_we;

endmodule

rtl/core/zba_unit.sv
module zba_unit (
    input  logic [63:0] rs1,
    input  logic [63:0] rs2,
    input  logic [2:0] funct3,
    output logic [63:0] result
);
    always_comb begin
        case (funct3)
            3'b010: result = rs1 + (rs2 << 1); // SH1ADD
            3'b100: result = rs1 + (rs2 << 2); // SH2ADD
            3'b110: result = rs1 + (rs2 << 3); // SH3ADD
            default: result = 64'b0;
        endcase
    end
endmodule

rtl/core/execute.sv
module execute (
    input  logic [63:0] rs1_data,
    input  logic [63:0] rs2_data,
    input  logic [63:0] imm,

    input  logic [6:0]  opcode,
    input  logic [2:0]  funct3,
    input  logic [6:0]  funct7,

    output logic [63:0] alu_result
);

    logic [63:0] zba_result;
    logic        is_zba;

    // Zba detection (OP opcode + funct7 = 0000100)
    assign is_zba = (opcode == 7'b0110011) && (funct7 == 7'b0000100);

    zba_unit zba (
        .rs1(rs1_data),
        .rs2(rs2_data),
        .funct3(funct3),
        .result(zba_result)
    );

    always_comb begin
        alu_result = 64'b0;

        if (is_zba) begin
            alu_result = zba_result;
        end else begin
            case (opcode)
                7'b0110011: begin // R-type
                    case (funct3)
                        3'b000: alu_result = (funct7 == 7'b0100000) ? rs1_data - rs2_data : rs1_data + rs2_data;
                        3'b111: alu_result = rs1_data & rs2_data;
                        3'b110: alu_result = rs1_data | rs2_data;
                        default: alu_result = 64'b0;
                    endcase
                end

                7'b0010011: begin // I-type
                    alu_result = rs1_data + imm;
                end

                default: alu_result = 64'b0;
            endcase
        end
    end

endmodule

rtl/core/regfile.sv
module regfile (
    input  logic clk,
    input  logic [4:0] rs1, rs2, rd,
    input  logic rd_we,
    input  logic [63:0] rd_data,
    output logic [63:0] rs1_data,
    output logic [63:0] rs2_data
);

    logic [63:0] regs [31:0];

    assign rs1_data = (rs1 == 0) ? 64'b0 : regs[rs1];
    assign rs2_data = (rs2 == 0) ? 64'b0 : regs[rs2];

    always_ff @(posedge clk) begin
        if (rd_we && rd != 0)
            regs[rd] <= rd_data;
    end

endmodule

rtl/core/decode.sv
module decode (
    input  logic [31:0] instr,

    output logic [6:0]  opcode,
    output logic [4:0]  rs1,
    output logic [4:0]  rs2,
    output logic [4:0]  rd,
    output logic [2:0]  funct3,
    output logic [6:0]  funct7,
    output logic [63:0] imm
);

    assign opcode = instr[6:0];
    assign rd     = instr[11:7];
    assign funct3 = instr[14:12];
    assign rs1    = instr[19:15];
    assign rs2    = instr[24:20];
    assign funct7 = instr[31:25];

    // I-type immediate
    assign imm = {{52{instr[31]}}, instr[31:20]};

endmodule

rtl/core/fetch.sv
module fetch (
    input  logic        clk,
    input  logic        rst,
    input  logic [63:0] pc_next,
    output logic [63:0] pc
);

    always_ff @(posedge clk or posedge rst) begin
        if (rst)
            pc <= 64'h0;
        else
            pc <= pc_next;
    end

endmodule

rtl/core/riscv_core.sv
module riscv_core (
    input  logic        clk,
    input  logic        rst,

    input  logic [31:0] instr_mem_rdata,
    output logic [63:0] instr_mem_addr,

    input  logic [63:0] data_mem_rdata,
    output logic [63:0] data_mem_addr,
    output logic [63:0] data_mem_wdata,
    output logic        data_mem_we
);

    // =====================
    // FETCH
    // =====================
    logic [63:0] pc, pc_next;
    assign pc_next = pc + 4;

    fetch if_stage (
        .clk(clk),
        .rst(rst),
        .pc_next(pc_next),
        .pc(pc)
    );

    assign instr_mem_addr = pc;

    // =====================
    // DECODE
    // =====================
    logic [6:0] opcode, funct7;
    logic [4:0] rs1, rs2, rd;
    logic [2:0] funct3;
    logic [63:0] imm;

    decode id_stage (
        .instr(instr_mem_rdata),
        .opcode(opcode),
        .rs1(rs1),
        .rs2(rs2),
        .rd(rd),
        .funct3(funct3),
        .funct7(funct7),
        .imm(imm)
    );

    // =====================
    // REGISTER FILE
    // =====================
    logic [63:0] rs1_data, rs2_data, rd_data;

    regfile rf (
        .clk(clk),
        .rs1(rs1),
        .rs2(rs2),
        .rd(rd),
        .rd_we(1'b1),
        .rd_data(rd_data),
        .rs1_data(rs1_data),
        .rs2_data(rs2_data)
    );

    // =====================
    // EXECUTE
    // =====================
    logic [63:0] alu_result;

    execute ex_stage (
        .rs1_data(rs1_data),
        .rs2_data(rs2_data),
        .imm(imm),
        .opcode(opcode),
        .funct3(funct3),
        .funct7(funct7),
        .alu_result(alu_result)
    );

    // =====================
    // MEMORY
    // =====================
    mem_stage mem_stage_i (
        .alu_result(alu_result),
        .rs2_data(rs2_data),
        .mem_we(1'b0),
        .data_mem_addr(data_mem_addr),
        .data_mem_wdata(data_mem_wdata),
        .data_mem_we(data_mem_we)
    );

    // =====================
    // WRITEBACK
    // =====================
    writeback wb_stage (
        .alu_result(alu_result),
        .mem_data(data_mem_rdata),
        .mem_to_reg(1'b0),
        .rd_data(rd_data)
    );

endmodule

rtl/top.sv
module top (
    input  logic clk,
    input  logic rst,

    input  logic [31:0] instr_mem_rdata,
    output logic [63:0] instr_mem_addr,

    input  logic [63:0] data_mem_rdata,
    output logic [63:0] data_mem_addr,
    output logic [63:0] data_mem_wdata,
    output logic        data_mem_we
);

    riscv_core core (
        .clk(clk),
        .rst(rst),
        .instr_mem_rdata(instr_mem_rdata),
        .instr_mem_addr(instr_mem_addr),
        .data_mem_rdata(data_mem_rdata),
        .data_mem_addr(data_mem_addr),
        .data_mem_wdata(data_mem_wdata),
        .data_mem_we(data_mem_we)
    );

endmodule

tb/tb_processor.sv
`timescale 1ns/1ps

module tb_processor;

    // =====================
    // Clock & Reset
    // =====================
    logic clk = 0;
    logic rst = 1;

    // =====================
    // Instruction memory
    // =====================
    logic [31:0] instr_mem [0:255];

    // =====================
    // DUT interface
    // =====================
    logic [63:0] instr_addr;
    logic [31:0] instr_data;

    // =====================
    // Clock generation
    // =====================
    always #5 clk = ~clk;   // 100 MHz

    // =====================
    // Instruction fetch
    // =====================
    assign instr_data = instr_mem[instr_addr >> 2];

    // =====================
    // DUT
    // =====================
    top dut (
        .clk(clk),
        .rst(rst),
        .instr_mem_rdata(instr_data),
        .instr_mem_addr(instr_addr),
        .data_mem_rdata(64'b0),
        .data_mem_addr(),
        .data_mem_wdata(),
        .data_mem_we()
    );

    integer i;

    initial begin
        // ---------------------
        // Waveform dump
        // ---------------------
        $dumpfile("wave.vcd");
        $dumpvars(0, tb_processor);

        // ---------------------
        // Initialize memory with NOPs
        // NOP = addi x0,x0,0 = 0x00000013
        // ---------------------
        for (i = 0; i < 256; i = i + 1)
            instr_mem[i] = 32'h00000013;

        // ---------------------
        // Load ONLY first N words from program.hex
        // This avoids Icarus warnings
        // ---------------------
        $readmemh("program.hex", instr_mem, 0, 255);
        // ^ loads at most 64 instructions

        // ---------------------
        // Reset
        // ---------------------
        rst = 1;
        #20;
        rst = 0;

        // ---------------------
        // Run
        // ---------------------
        #500;

        $display("=================================");
        $display("Simulation PASSED");
        $display("=================================");
        $finish;
    end

    // =====================
    // Debug trace
    // =====================
    always @(posedge clk) begin
        if (!rst) begin
            $display("TIME=%0t | PC=0x%08h | INSTR=0x%08h",
                     $time, instr_addr, instr_data);
        end
    end

endmodule

wave.vcd
$date
	Mon Jan 19 15:35:10 2026
$end
$version
	Icarus Verilog
$end
$timescale
	1ps
$end
$scope module tb_processor $end
$var wire 32 ! instr_data [31:0] $end
$var wire 64 " instr_addr [63:0] $end
$var reg 1 # clk $end
$var reg 1 $ rst $end
$var integer 32 % i [31:0] $end
$scope module dut $end
$var wire 1 # clk $end
$var wire 64 & data_mem_rdata [63:0] $end
$var wire 32 ' instr_mem_rdata [31:0] $end
$var wire 1 $ rst $end
$var wire 64 ( instr_mem_addr [63:0] $end
$var wire 1 ) data_mem_we $end
$var wire 64 * data_mem_wdata [63:0] $end
$var wire 64 + data_mem_addr [63:0] $end
$scope module core $end
$var wire 1 # clk $end
$var wire 64 , data_mem_rdata [63:0] $end
$var wire 64 - instr_mem_addr [63:0] $end
$var wire 32 . instr_mem_rdata [31:0] $end
$var wire 1 $ rst $end
$var wire 64 / rs2_data [63:0] $end
$var wire 5 0 rs2 [4:0] $end
$var wire 64 1 rs1_data [63:0] $end
$var wire 5 2 rs1 [4:0] $end
$var wire 64 3 rd_data [63:0] $end
$var wire 5 4 rd [4:0] $end
$var wire 64 5 pc_next [63:0] $end
$var wire 64 6 pc [63:0] $end
$var wire 7 7 opcode [6:0] $end
$var wire 64 8 imm [63:0] $end
$var wire 7 9 funct7 [6:0] $end
$var wire 3 : funct3 [2:0] $end
$var wire 1 ) data_mem_we $end
$var wire 64 ; data_mem_wdata [63:0] $end
$var wire 64 < data_mem_addr [63:0] $end
$var wire 64 = alu_result [63:0] $end
$scope module ex_stage $end
$var wire 1 > is_zba $end
$var wire 64 ? zba_result [63:0] $end
$var wire 64 @ rs2_data [63:0] $end
$var wire 64 A rs1_data [63:0] $end
$var wire 7 B opcode [6:0] $end
$var wire 64 C imm [63:0] $end
$var wire 7 D funct7 [6:0] $end
$var wire 3 E funct3 [2:0] $end
$var reg 64 F alu_result [63:0] $end
$scope module zba $end
$var wire 64 G rs2 [63:0] $end
$var wire 64 H rs1 [63:0] $end
$var wire 3 I funct3 [2:0] $end
$var reg 64 J result [63:0] $end
$upscope $end
$upscope $end
$scope module id_stage $end
$var wire 32 K instr [31:0] $end
$var wire 5 L rs2 [4:0] $end
$var wire 5 M rs1 [4:0] $end
$var wire 5 N rd [4:0] $end
$var wire 7 O opcode [6:0] $end
$var wire 64 P imm [63:0] $end
$var wire 7 Q funct7 [6:0] $end
$var wire 3 R funct3 [2:0] $end
$upscope $end
$scope module if_stage $end
$var wire 1 # clk $end
$var wire 64 S pc_next [63:0] $end
$var wire 1 $ rst $end
$var reg 64 T pc [63:0] $end
$upscope $end
$scope module mem_stage_i $end
$var wire 64 U alu_result [63:0] $end
$var wire 64 V data_mem_addr [63:0] $end
$var wire 64 W data_mem_wdata [63:0] $end
$var wire 1 ) data_mem_we $end
$var wire 1 X mem_we $end
$var wire 64 Y rs2_data [63:0] $end
$upscope $end
$scope module rf $end
$var wire 1 # clk $end
$var wire 5 Z rd [4:0] $end
$var wire 1 [ rd_we $end
$var wire 5 \ rs1 [4:0] $end
$var wire 5 ] rs2 [4:0] $end
$var wire 64 ^ rs2_data [63:0] $end
$var wire 64 _ rs1_data [63:0] $end
$var wire 64 ` rd_data [63:0] $end
$upscope $end
$scope module wb_stage $end
$var wire 64 a alu_result [63:0] $end
$var wire 64 b mem_data [63:0] $end
$var wire 1 c mem_to_reg $end
$var wire 64 d rd_data [63:0] $end
$upscope $end
$upscope $end
$upscope $end
$upscope $end
$enddefinitions $end
$comment Show the parameter values. $end
$dumpall
$end
#0
$dumpvars
b0 d
0c
b0 b
b0 a
b0 `
bx _
bx ^
bx ]
bx \
1[
bx Z
bx Y
0X
bx W
b0 V
b0 U
bx T
bx S
bx R
bx Q
bx P
bx O
bx N
bx M
bx L
bx K
b0 J
bx I
bx H
bx G
b0 F
bx E
bx D
bx C
bx B
bx A
bx @
b0 ?
x>
b0 =
b0 <
bx ;
bx :
bx 9
bx 8
bx 7
bx 6
bx 5
bx 4
b0 3
bx 2
bx 1
bx 0
bx /
bx .
bx -
b0 ,
b0 +
bx *
0)
bx (
bx '
b0 &
b100000000 %
1$
0#
bx "
bx !
$end
#5000
b0 1
b0 A
b0 H
b0 _
b0 *
b0 ;
b0 W
b0 /
b0 @
b0 G
b0 Y
b0 ^
0>
b0 +
b0 <
b0 V
b0 3
b0 `
b0 d
b0 =
b0 F
b0 U
b0 a
b10011 7
b10011 B
b10011 O
b0 4
b0 N
b0 Z
b0 :
b0 E
b0 I
b0 R
b0 2
b0 M
b0 \
b0 0
b0 L
b0 ]
b0 9
b0 D
b0 Q
b0 8
b0 C
b0 P
b10011 !
b10011 '
b10011 .
b10011 K
b100 5
b100 S
b0 "
b0 (
b0 -
b0 6
b0 T
1#
#10000
0#
#15000
1#
#20000
0#
0$
#25000
b1000 5
b1000 S
b100 "
b100 (
b100 -
b100 6
b100 T
1#
#30000
0#
#35000
b1100 5
b1100 S
b1000 "
b1000 (
b1000 -
b1000 6
b1000 T
1#
#40000
0#
#45000
b10000 5
b10000 S
b1100 "
b1100 (
b1100 -
b1100 6
b1100 T
1#
#50000
0#
#55000
b10100 5
b10100 S
b10000 "
b10000 (
b10000 -
b10000 6
b10000 T
1#
#60000
0#
#65000
b11000 5
b11000 S
b10100 "
b10100 (
b10100 -
b10100 6
b10100 T
1#
#70000
0#
#75000
b11100 5
b11100 S
b11000 "
b11000 (
b11000 -
b11000 6
b11000 T
1#
#80000
0#
#85000
b100000 5
b100000 S
b11100 "
b11100 (
b11100 -
b11100 6
b11100 T
1#
#90000
0#
#95000
b100100 5
b100100 S
b100000 "
b100000 (
b100000 -
b100000 6
b100000 T
1#
#100000
0#
#105000
b101000 5
b101000 S
b100100 "
b100100 (
b100100 -
b100100 6
b100100 T
1#
#110000
0#
#115000
b101100 5
b101100 S
b101000 "
b101000 (
b101000 -
b101000 6
b101000 T
1#
#120000
0#
#125000
b110000 5
b110000 S
b101100 "
b101100 (
b101100 -
b101100 6
b101100 T
1#
#130000
0#
#135000
b110100 5
b110100 S
b110000 "
b110000 (
b110000 -
b110000 6
b110000 T
1#
#140000
0#
#145000
b111000 5
b111000 S
b110100 "
b110100 (
b110100 -
b110100 6
b110100 T
1#
#150000
0#
#155000
b111100 5
b111100 S
b111000 "
b111000 (
b111000 -
b111000 6
b111000 T
1#
#160000
0#
#165000
b1000000 5
b1000000 S
b111100 "
b111100 (
b111100 -
b111100 6
b111100 T
1#
#170000
0#
#175000
b1000100 5
b1000100 S
b1000000 "
b1000000 (
b1000000 -
b1000000 6
b1000000 T
1#
#180000
0#
#185000
b1001000 5
b1001000 S
b1000100 "
b1000100 (
b1000100 -
b1000100 6
b1000100 T
1#
#190000
0#
#195000
b1001100 5
b1001100 S
b1001000 "
b1001000 (
b1001000 -
b1001000 6
b1001000 T
1#
#200000
0#
#205000
b1010000 5
b1010000 S
b1001100 "
b1001100 (
b1001100 -
b1001100 6
b1001100 T
1#
#210000
0#
#215000
b1010100 5
b1010100 S
b1010000 "
b1010000 (
b1010000 -
b1010000 6
b1010000 T
1#
#220000
0#
#225000
b1011000 5
b1011000 S
b1010100 "
b1010100 (
b1010100 -
b1010100 6
b1010100 T
1#
#230000
0#
#235000
b1011100 5
b1011100 S
b1011000 "
b1011000 (
b1011000 -
b1011000 6
b1011000 T
1#
#240000
0#
#245000
b1100000 5
b1100000 S
b1011100 "
b1011100 (
b1011100 -
b1011100 6
b1011100 T
1#
#250000
0#
#255000
b1100100 5
b1100100 S
b1100000 "
b1100000 (
b1100000 -
b1100000 6
b1100000 T
1#
#260000
0#
#265000
b1101000 5
b1101000 S
b1100100 "
b1100100 (
b1100100 -
b1100100 6
b1100100 T
1#
#270000
0#
#275000
b1101100 5
b1101100 S
b1101000 "
b1101000 (
b1101000 -
b1101000 6
b1101000 T
1#
#280000
0#
#285000
b1110000 5
b1110000 S
b1101100 "
b1101100 (
b1101100 -
b1101100 6
b1101100 T
1#
#290000
0#
#295000
b1110100 5
b1110100 S
b1110000 "
b1110000 (
b1110000 -
b1110000 6
b1110000 T
1#
#300000
0#
#305000
b1111000 5
b1111000 S
b1110100 "
b1110100 (
b1110100 -
b1110100 6
b1110100 T
1#
#310000
0#
#315000
b1111100 5
b1111100 S
b1111000 "
b1111000 (
b1111000 -
b1111000 6
b1111000 T
1#
#320000
0#
#325000
b10000000 5
b10000000 S
b1111100 "
b1111100 (
b1111100 -
b1111100 6
b1111100 T
1#
#330000
0#
#335000
b10000100 5
b10000100 S
b10000000 "
b10000000 (
b10000000 -
b10000000 6
b10000000 T
1#
#340000
0#
#345000
b10001000 5
b10001000 S
b10000100 "
b10000100 (
b10000100 -
b10000100 6
b10000100 T
1#
#350000
0#
#355000
b10001100 5
b10001100 S
b10001000 "
b10001000 (
b10001000 -
b10001000 6
b10001000 T
1#
#360000
0#
#365000
b10010000 5
b10010000 S
b10001100 "
b10001100 (
b10001100 -
b10001100 6
b10001100 T
1#
#370000
0#
#375000
b10010100 5
b10010100 S
b10010000 "
b10010000 (
b10010000 -
b10010000 6
b10010000 T
1#
#380000
0#
#385000
b10011000 5
b10011000 S
b10010100 "
b10010100 (
b10010100 -
b10010100 6
b10010100 T
1#
#390000
0#
#395000
b10011100 5
b10011100 S
b10011000 "
b10011000 (
b10011000 -
b10011000 6
b10011000 T
1#
#400000
0#
#405000
b10100000 5
b10100000 S
b10011100 "
b10011100 (
b10011100 -
b10011100 6
b10011100 T
1#
#410000
0#
#415000
b10100100 5
b10100100 S
b10100000 "
b10100000 (
b10100000 -
b10100000 6
b10100000 T
1#
#420000
0#
#425000
b10101000 5
b10101000 S
b10100100 "
b10100100 (
b10100100 -
b10100100 6
b10100100 T
1#
#430000
0#
#435000
b10101100 5
b10101100 S
b10101000 "
b10101000 (
b10101000 -
b10101000 6
b10101000 T
1#
#440000
0#
#445000
b10110000 5
b10110000 S
b10101100 "
b10101100 (
b10101100 -
b10101100 6
b10101100 T
1#
#450000
0#
#455000
b10110100 5
b10110100 S
b10110000 "
b10110000 (
b10110000 -
b10110000 6
b10110000 T
1#
#460000
0#
#465000
b10111000 5
b10111000 S
b10110100 "
b10110100 (
b10110100 -
b10110100 6
b10110100 T
1#
#470000
0#
#475000
b10111100 5
b10111100 S
b10111000 "
b10111000 (
b10111000 -
b10111000 6
b10111000 T
1#
#480000
0#
#485000
b11000000 5
b11000000 S
b10111100 "
b10111100 (
b10111100 -
b10111100 6
b10111100 T
1#
#490000
0#
#495000
b11000100 5
b11000100 S
b11000000 "
b11000000 (
b11000000 -
b11000000 6
b11000000 T
1#
#500000
0#
#505000
b11001000 5
b11001000 S
b11000100 "
b11000100 (
b11000100 -
b11000100 6
b11000100 T
1#
#510000
0#
#515000
b11001100 5
b11001100 S
b11001000 "
b11001000 (
b11001000 -
b11001000 6
b11001000 T
1#
